pyvision3/__init__.py
pyvision3/affine.py
pyvision3/constants.py
pyvision3/geometry.py
pyvision3/image.py
pyvision3/imagebuffer.py
pyvision3/montage.py
pyvision3/pv_exceptions.py
pyvision3/video.py
pyvision3/data/driveway.jpg
pyvision3/data/prius_gray.jpg
pyvision3/data/prius_movie.mov
pyvision3/data/project_info.json
pyvision3/data/sleepycat.jpg
pyvision3/data/test_mask.tif
pyvision3/dataset_tools/__init__.py
pyvision3/dataset_tools/capture_clicks.py
pyvision3/dataset_tools/capture_polygons.py
pyvision3/dataset_tools/crops.py
pyvision3/dataset_tools/tile_selection.py
pyvision3/video_proc/__init__.py
pyvision3/video_proc/backgroundsubtract.py
pyvision3/video_proc/motiondetection.py
tests/__init__.py
tests/test_affine.py
tests/test_dataset_tools.py
tests/test_image.py
tests/test_image_buffer.py
tests/test_video.py
pyvision3-0.1.8.dist-info/LICENSE.txt
pyvision3-0.1.8.dist-info/METADATA
pyvision3-0.1.8.dist-info/WHEEL
pyvision3-0.1.8.dist-info/top_level.txt
pyvision3-0.1.8.dist-info/RECORD
