Metadata-Version: 2.1
Name: pyvision3
Version: 0.1.8
Summary: Facilitates computer vision research and prototyping using python and openCV
Home-page: https://github.com/svohara/pyvision3
Author: Stephen O'Hara
Author-email: svohara@gmail.com
License: MIT
Download-URL: https://github.com/svohara/pyvision3/archive/0.1.8.tar.gz
Keywords: images video vision
Platform: UNKNOWN
Classifier: Development Status :: 4 - Beta
Classifier: Intended Audience :: Developers
Classifier: License :: OSI Approved :: MIT License
Classifier: Programming Language :: Python :: 3
Requires-Python: >=3.6
Requires-Dist: matplotlib (>=1.3.1)
Requires-Dist: numpy (>=1.8.2)
Requires-Dist: pillow (>=2.3.0)
Requires-Dist: shapely (>=1.3.0)
Requires-Dist: opencv-python
